fetch_import/__init__.py
fetch_import/api.py
fetch_import/main.py
fetch_import-0.0.9.dist-info/LICENSE
fetch_import-0.0.9.dist-info/METADATA
fetch_import-0.0.9.dist-info/WHEEL
fetch_import-0.0.9.dist-info/top_level.txt
fetch_import-0.0.9.dist-info/RECORD
