Metadata-Version: 2.1
Name: fetch-import
Version: 0.0.9
Summary: Import Python packages from remote.
Home-page: https://github.com/zmaplex/fetch_import
Author: zmaplex
Author-email: zmaplex@gmail.com
License: UNKNOWN
Platform: UNKNOWN
Requires-Python: >=3.6
License-File: LICENSE
